{
  "title": "Antares Programming",
  "description": "For Filipino web developers",
  "baseUrl": "http://localhost:8080",
  "seo": {
    "og": {
      "src": ""
    },
    "twitter": {
      "src": ""
    }
  },
  "contact": {
    "email": {
      "name": "Email",
      "identifier": "hello@antaresph.dev",
      "url": "mailto:hello@antaresph.dev"
    },
    "instagram": {
      "name": "Instagram",
      "identifier": "@antaresphdev",
      "url": "https://instagram.com/antaresphdev"
    },
    "mastodon": {
      "name": "Mastodon",
      "identifier": "@antaresphdev@mas.to",
      "url": "https://mas.to/@antaresphdev"
    },
    "youtube": {
      "name": "YouTube",
      "identifier": "@antaresphdev",
      "url": "https://youtube.com/@antaresphdev"
    },
    "tiktok": {
      "name": "Tiktok",
      "identifier": "@antaresphdev",
      "url": "https://tiktok.com/@antaresphdev"
    },
    "codepen": {
      "name": "CodePen",
      "identifier": "@antaresphdev",
      "url": "https://codepen.io/antaresphdev"
    }
  },
  "domains": [
    {
      "name": "Cloudflare",
      "domain": "antaresph.dev",
      "isPreferred": true
    }
  ],
  "api": {
    "email": "",
    "siteData": "/api/v1/site-data.json",
    "images": "https://ik.imagekit.io/antaresphdev"
  }
}